MANIFEST.in
README.md
ouroboros
requirements.txt
setup.py
ouroboros_cli.egg-info/PKG-INFO
ouroboros_cli.egg-info/SOURCES.txt
ouroboros_cli.egg-info/dependency_links.txt
ouroboros_cli.egg-info/requires.txt
ouroboros_cli.egg-info/top_level.txt
pyouroboros/__init__.py
pyouroboros/config.py
pyouroboros/dataexporters.py
pyouroboros/dockerclient.py
pyouroboros/helpers.py
pyouroboros/logger.py
pyouroboros/notifiers.py
pyouroboros/ouroboros.py