Metadata-Version: 2.1
Name: ouroboros-cli
Version: 1.4.1
Summary: Automatically update running docker containers
Home-page: https://github.com/pyouroboros/ouroboros
Maintainer: circa10a
Maintainer-email: caleblemoine@gmail.com
License: MIT
Platform: UNKNOWN
Classifier: Programming Language :: Python
Classifier: Programming Language :: Python :: 3.6
Classifier: Programming Language :: Python :: 3.7
Requires-Python: >=3.6.2
